fireflyConverter/__init__.py
fireflyConverter/__main__.py
fireflyConverter/cli.py
fireflyConverter/convertData.py
fireflyConverter/data.py
fireflyConverter/fireflyInterface.py
fireflyConverter/fireflyPayload.py
fireflyConverter/loadData.py
firefly_cash_converter-0.2.0.dist-info/licenses/LICENSE
firefly_cash_converter-0.2.0.dist-info/METADATA
firefly_cash_converter-0.2.0.dist-info/WHEEL
firefly_cash_converter-0.2.0.dist-info/entry_points.txt
firefly_cash_converter-0.2.0.dist-info/top_level.txt
firefly_cash_converter-0.2.0.dist-info/RECORD
