Metadata-Version: 2.4
Name: firefly-cash-converter
Version: 0.2.0
Summary: A tool to convert financial data for Firefly III
Author-email: Philip Dorpmüller <philip.dorpmueller@wb.de>
License: MIT
Classifier: Programming Language :: Python :: 3
Classifier: Programming Language :: Python :: 3.11
Requires-Python: >=3.11
License-File: LICENSE
Requires-Dist: pandas
Requires-Dist: numpy
Requires-Dist: openpyxl
Requires-Dist: toml
Requires-Dist: requests
Provides-Extra: dev
Requires-Dist: python-dotenv; extra == "dev"
Requires-Dist: pytest; extra == "dev"
Requires-Dist: pytest-cov; extra == "dev"
Provides-Extra: test
Requires-Dist: python-dotenv; extra == "test"
Requires-Dist: pytest; extra == "test"
Dynamic: license-file
